python3_youtrack_api/__init__.py
python3_youtrack_api/auth.py
python3_youtrack_api/client.py
python3_youtrack_api/exceptions.py
python3_youtrack_api/handlers.py
python3_youtrack_api/models.py
python3_youtrack_api/schema.py
Python3_Youtrack_api-0.2.dist-info/METADATA
Python3_Youtrack_api-0.2.dist-info/WHEEL
Python3_Youtrack_api-0.2.dist-info/top_level.txt
Python3_Youtrack_api-0.2.dist-info/RECORD
